cvlearn/FaceDetection.py
cvlearn/FaceMesh.py
cvlearn/FingerCounter.py
cvlearn/HandTrackingModule.py
cvlearn/PoseDetector.py
cvlearn/TwoHandsFingerCounter.py
cvlearn/Utils.py
cvlearn/__init__.py
cvlearn-0.4.3.dist-info/METADATA
cvlearn-0.4.3.dist-info/WHEEL
cvlearn-0.4.3.dist-info/top_level.txt
cvlearn-0.4.3.dist-info/RECORD
