Metadata-Version: 2.1
Name: cvlearn
Version: 0.4.3
Summary: Coumputer Vision helping Library
Author: ErrorCode (Tanay)
Author-email: codingkaku@gmail.com
Keywords: python,opencv,computer vision,cv2,image processing,mediapipe,pose detection,face mesh,hand tracking,cvlearn
Classifier: Development Status :: 4 - Beta
Classifier: Intended Audience :: Developers
Classifier: License :: OSI Approved :: MIT License
Classifier: Programming Language :: Python :: 3
Classifier: Programming Language :: Python :: 3.7
Classifier: Programming Language :: Python :: 3.8
Classifier: Programming Language :: Python :: 3.9
Classifier: Programming Language :: Python :: 3.10
Classifier: Operating System :: OS Independent
Classifier: Topic :: Software Development :: Libraries :: Python Modules
Classifier: Topic :: Multimedia :: Video
Requires-Dist: numpy
Requires-Dist: opencv-python
Requires-Dist: opencv-contrib-python
Requires-Dist: mediapipe
